MANIFEST.in
README.rst
setup.py
django_selenium/__init__.py
django_selenium/jenkins_runner.py
django_selenium/livetestcases.py
django_selenium/selenium_runner.py
django_selenium/selenium_server.py
django_selenium/settings.py
django_selenium/testcases.py
django_selenium.egg-info/PKG-INFO
django_selenium.egg-info/SOURCES.txt
django_selenium.egg-info/dependency_links.txt
django_selenium.egg-info/top_level.txt
django_selenium.egg-info/zip-safe
django_selenium/management/__init__.py
django_selenium/management/commands/__init__.py
django_selenium/management/commands/test_selenium.py
tests/__init__.py
tests/manage.py
tests/settings.py
tests/urls.py
tests/core/__init__.py
tests/core/forms.py
tests/core/models.py
tests/core/tests.py
tests/core/views.py
tests/core/management/__init__.py
tests/core/management/commands/__init__.py
tests/core/management/commands/test.py